<?xml version = '1.0' encoding = 'UTF-8'?>
<Relation class="oracle.dbtools.crest.model.design.logical.Relation" name="Relation_2" directorySegmentName="seg_0" id="DAC224A4-128A-A684-E631-2F1A71C62900">
<createdBy>ricky</createdBy>
<createdTime>2017-02-16 00:19:07 UTC</createdTime>
<ownerDesignName>logical_model</ownerDesignName>
<engineerTo>
<item key="C71330CF-CA4E-6F6A-EC81-9A8451421595" value="true"/>
</engineerTo>
<identifying>false</identifying>
<optionalSource>true</optionalSource>
<optionalTarget>true</optionalTarget>
<sourceCardinality>*</sourceCardinality>
<sourceEntity>4789BC18-465A-C6E2-9DA9-8FB2B6F1F4A6</sourceEntity>
<targetCardinalityString>*</targetCardinalityString>
<targetEntity>FA1B92CE-B190-4928-5628-0D694A752CB4</targetEntity>
<transferable>true</transferable>
<deleteRule>NO ACTION</deleteRule>
</Relation>